scikits/bootstrap/__init__.py
scikits/bootstrap/bootstrap.py
scikits/bootstrap/py.typed
scikits_bootstrap-1.1.1.dist-info/METADATA
scikits_bootstrap-1.1.1.dist-info/WHEEL
scikits_bootstrap-1.1.1.dist-info/licenses/LICENSE
scikits_bootstrap-1.1.1.dist-info/RECORD
