Metadata-Version: 2.4
Name: scikits.bootstrap
Version: 1.1.1
Summary: Bootstrap confidence interval estimation routines for Numpy/Scipy/Pandas
Project-URL: Homepage, http://github.com/cgevans/scikits-bootstrap
Project-URL: Repository, http://github.com/cgevans/scikits-bootstrap
Project-URL: Documentation, https://scikits-bootstrap.readthedocs.io/
Project-URL: Issues, https://github.com/cgevans/scikits-bootstrap/issues
Author-email: Constantine Evans <cevans@costinet.org>
License-Expression: BSD-3-Clause
License-File: LICENSE
Classifier: Development Status :: 5 - Production/Stable
Classifier: Environment :: Console
Classifier: Intended Audience :: Developers
Classifier: Intended Audience :: Science/Research
Classifier: License :: OSI Approved :: BSD License
Classifier: Operating System :: OS Independent
Classifier: Programming Language :: Python
Classifier: Programming Language :: Python :: 3
Classifier: Programming Language :: Python :: 3.8
Classifier: Programming Language :: Python :: 3.9
Classifier: Programming Language :: Python :: 3.10
Classifier: Programming Language :: Python :: 3.11
Classifier: Programming Language :: Python :: 3.12
Classifier: Programming Language :: Python :: 3.13
Classifier: Programming Language :: Python :: Implementation :: CPython
Classifier: Programming Language :: Python :: Implementation :: PyPy
Classifier: Topic :: Scientific/Engineering
Classifier: Typing :: Typed
Requires-Python: >=3.7
Requires-Dist: numpy>=1.22.0
Requires-Dist: typing-extensions>=4.1; python_version < '3.10'
